spinalcord/__init__.py
spinalcord/exceptions.py
spinalcord/fields/__init__.py
spinalcord/fields/base.py
spinalcord/fields/double.py
spinalcord/fields/int32.py
spinalcord/fields/uint16.py
spinalcord/models/__init__.py
spinalcord/models/base.py
spinalcord/utils/__init__.py
spinalcord/utils/bytebuffer.py
spinalcord/utils/byteconverter.py
spinalcord-1.0.0.dist-info/LICENSE
spinalcord-1.0.0.dist-info/METADATA
spinalcord-1.0.0.dist-info/WHEEL
spinalcord-1.0.0.dist-info/top_level.txt
spinalcord-1.0.0.dist-info/RECORD
