Metadata-Version: 2.1
Name: spinalcord
Version: 1.0.0
Summary: SpinalCord SDK for Python
License: Apache License
Project-URL: Homepage, https://github.com/Lepta-Technologies/spinalcord-py
Keywords: python,spinalcord,lepta-technologies
Classifier: License :: OSI Approved :: Apache Software License
Classifier: Topic :: Software Development :: Libraries :: Python Modules
Classifier: Programming Language :: Python :: 3.11
Requires-Python: >=3.8
License-File: LICENSE
